LICENSE
LICENSE.txt
MANIFEST.in
README.md
setup.cfg
setup.py
licenses/markdown
licenses/pygments
licenses/tabulate
mdv/__init__.py
mdv/ansi_tables.json
mdv/markdownviewer.py
mdv/tabulate.py
mdv.egg-info/PKG-INFO
mdv.egg-info/SOURCES.txt
mdv.egg-info/dependency_links.txt
mdv.egg-info/entry_points.txt
mdv.egg-info/requires.txt
mdv.egg-info/top_level.txt
tests/__init__.py
tests/test_files.py
tests/test_inline.py