Metadata-Version: 2.1
Name: mdv
Version: 1.7.5
Summary: Terminal Markdown Viewer
Home-page: http://github.com/axiros/terminal_markdown_viewer
Download-URL: http://github.com/axiros/terminal_markdown_viewer/tarball/
Author: Axiros GmbH
Author-email: gk@axiros.com
Keywords: markdown,markup,terminal,hilighting,syntax,source code
Classifier: Programming Language :: Python
Classifier: Natural Language :: English
Classifier: Operating System :: POSIX
Classifier: Topic :: Text Processing :: Markup
Classifier: License :: OSI Approved :: BSD License
Classifier: Programming Language :: Python :: 2.7
Classifier: Programming Language :: Python :: 3
Classifier: Programming Language :: Python :: 3.6
Classifier: Programming Language :: Python :: 3.7
Classifier: Programming Language :: Python :: 3.8
Classifier: Programming Language :: Python :: 3.9
Classifier: Programming Language :: Python :: 3.10
Classifier: Programming Language :: Python :: 3.11
Classifier: Programming Language :: Python :: 3.12
Provides-Extra: yaml
License-File: LICENSE
License-File: LICENSE.txt
